django_request_approval/__init__.py
django_request_approval/apps.py
django_request_approval/exceptions.py
django_request_approval/forms.py
django_request_approval/models.py
django_request_approval/services.py
django_request_approval-1.0.2.dist-info/METADATA
django_request_approval-1.0.2.dist-info/WHEEL
django_request_approval-1.0.2.dist-info/licenses/LICENSE
django_request_approval-1.0.2.dist-info/RECORD
