Metadata-Version: 2.3
Name: django_request_approval
Version: 1.0.2
Summary: Django Request Approval Process
Project-URL: Homepage, https://github.com/briansimpo/django-request-approval
Project-URL: Issues, https://github.com/briansimpo/django-request-approval/issues
Author-email: Brian Simpokolwe <briansimpokolwe@gmail.com>
Keywords: approval,django approval
Classifier: License :: OSI Approved :: MIT License
Classifier: Operating System :: OS Independent
Classifier: Programming Language :: Python :: 3.10
Requires-Python: >=3.10
Requires-Dist: django-model-utils>=4.5.1
Requires-Dist: django>=4.0.0
